{
  "orders": [
    { "ID": 1, "madeBy": 1, "orderStatusID": 1, "createdDate": "1537556613804" },
    { "ID": 1, "madeBy": 2, "orderStatusID": 1, "createdDate": "1537556627126" },
    { "ID": 1, "madeBy": 1, "orderStatusID": 1, "createdDate": "1537556707018" },
    { "ID": 1, "madeBy": 3, "orderStatusID": 1, "createdDate": "1537556714499" },
    { "ID": 1, "madeBy": 3, "orderStatusID": 1, "createdDate": "1537556720694" },
    { "ID": 1, "madeBy": 2, "orderStatusID": 1, "createdDate": "1537556726324" },
    { "ID": 1, "madeBy": 1, "orderStatusID": 1, "createdDate": "1537556732554" }
  ],
  "comments": [
    { "id": 1, "body": "some comment", "postId": 1 },
    { "id": 2, "body": "some comment", "postId": 1 }
  ],
  "profile": {
    "name": "typicode"
  }
}
